phorm/__init__.py
phorm-1.0.1.dist-info/LICENSE
phorm-1.0.1.dist-info/METADATA
phorm-1.0.1.dist-info/WHEEL
phorm-1.0.1.dist-info/top_level.txt
phorm-1.0.1.dist-info/RECORD
