Metadata-Version: 2.1
Name: phorm
Version: 1.0.1
Summary: help you fill form automatically
Author: Denon
Author-email: denon@xueyuan.dev
Classifier: Programming Language :: Python :: 3
Classifier: License :: OSI Approved :: MIT License
Classifier: Operating System :: OS Independent
Requires-Python: >=3.6
License-File: LICENSE
Requires-Dist: requests
Requires-Dist: beautifulsoup4
